Metadata-Version: 1.0
Name: ice-yml-log-formatter
Version: 0.1.1
Summary: ZeroC Ice logging utils
Home-page: https://github.com/3g0r/ice-yml-log-formatter
Author: 3g0r
Author-email: eg0r.n1k0l43v@gmail.com
License: MIT
Keywords: ice,yml,log
Platform: UNKNOWN
